pydfy/__init__.py
pydfy/models.py
pydfy/renderer.py
pydfy/template/package.json
pydfy/template/src/base.css
pydfy/template/src/partials/image.html
pydfy/template/src/partials/number.html
pydfy/template/src/partials/pagebreak.html
pydfy/template/src/partials/paragraph.html
pydfy/template/src/partials/section.html
pydfy/template/src/partials/table.html
pydfy/template/src/partials/title.html
pydfy/template/src/template.html
pydfy-0.2.0.dist-info/LICENSE
pydfy-0.2.0.dist-info/METADATA
pydfy-0.2.0.dist-info/WHEEL
pydfy-0.2.0.dist-info/RECORD
