Metadata-Version: 2.1
Name: pydfy
Version: 0.2.0
Summary: PDF reporting made easy.
Home-page: https://github.com/BiteStreams/pydfy
License: MIT
Author: Donny Peeters
Author-email: donny@bitestreams.com
Requires-Python: >=3.10,<4.0
Classifier: License :: OSI Approved :: MIT License
Classifier: Programming Language :: Python :: 3
Classifier: Programming Language :: Python :: 3.10
Classifier: Programming Language :: Python :: 3.11
Classifier: Programming Language :: Python :: 3.12
Provides-Extra: matplotlib
Provides-Extra: pandas
Provides-Extra: polars
Requires-Dist: jinja2 (>=3.1.4,<4.0.0)
Requires-Dist: matplotlib (>=3.0.0,<4.0.0) ; extra == "matplotlib"
Requires-Dist: pandas (>=2.0.0,<3.0.0) ; extra == "pandas"
Requires-Dist: polars (>=0.20.30,<0.21.0) ; extra == "polars"
Requires-Dist: selenium (>=4.18.1,<5.0.0)
Project-URL: Repository, https://github.com/BiteStreams/pydfy
